libcfds/ceulerianfluxes.c
libcfds/ceulerianfluxes.h
libcfds/cfields.c
libcfds/cfields.h
libcfds/cfilters.c
libcfds/cfilters.h
libcfds/cobjects.h
libcfds/coefficients.h
libcfds/cviscousfluxes.c
libcfds/cviscousfluxes.h
libcfds/kernels_diffadd.c
libcfds/kernels_diffadd.h
libcfds/kernels_diffcpy.c
libcfds/kernels_diffcpy.h
libcfds/kernels_diffraw.c
libcfds/kernels_diffraw.h
libcfds/kernels_diffsub.c
libcfds/kernels_diffsub.h
libcfds/kernels_sc.c
libcfds/kernels_sc.h
libcfds/kernels_sf.c
libcfds/kernels_sf.h
libfds/__init__.pxd
libfds/__init__.py
libfds/cfdtd.c
libfds/cfdtd.cpython-311-darwin.so
libfds/cfdtd.pxd
libfds/cmaths.c
libfds/cmaths.cpython-311-darwin.so
libfds/cmaths.pxd
libfds/cutils.c
libfds/cutils.cpython-311-darwin.so
libfds/cutils.pxd
libfds/filters.c
libfds/filters.cpython-311-darwin.so
libfds/filters.pxd
libfds/includes.pxd
libfds-1.0.0.dist-info/METADATA
libfds-1.0.0.dist-info/WHEEL
libfds-1.0.0.dist-info/top_level.txt
libfds-1.0.0.dist-info/RECORD
