Metadata-Version: 2.1
Name: libfds
Version: 1.0.0
Summary: "Finite difference library used by nsfds2/3",
Author: Cyril Desjouy
Author-email: cyril.desjouy@univ-lemans.fr
License: GPL
Classifier: Development Status :: 4 - Beta
Classifier: Programming Language :: Python :: 3
Classifier: Intended Audience :: Science/Research
Classifier: Topic :: Scientific/Engineering :: Physics
Classifier: Topic :: Software Development :: Libraries :: Python Modules
Classifier: License :: OSI Approved :: GNU General Public License v3 or later (GPLv3+)
Requires-Dist: numpy
